vidispine/__init__.py
vidispine/base.py
vidispine/client.py
vidispine/collections.py
vidispine/errors.py
vidispine/items.py
vidispine/jobs.py
vidispine/log.py
vidispine/metadata.py
vidispine/search.py
vidispine/shape_tag.py
vidispine/storage.py
vidispine/typing.py
vidispine/utils.py
vidispine_adapter-0.0.6.dist-info/LICENSE
vidispine_adapter-0.0.6.dist-info/WHEEL
vidispine_adapter-0.0.6.dist-info/METADATA
vidispine_adapter-0.0.6.dist-info/RECORD
