Metadata-Version: 2.1
Name: vidispine-adapter
Version: 0.0.6
Summary: Python Vidispine API Adapter
Home-page: https://github.com/newmediaresearch/vidispine-adapter
License: MIT
Author: NMR
Author-email: developers@nmr.com
Requires-Python: >=3.6,<4.0
Classifier: License :: OSI Approved :: MIT License
Classifier: Programming Language :: Python :: 3
Classifier: Programming Language :: Python :: 3.6
Classifier: Programming Language :: Python :: 3.7
Classifier: Programming Language :: Python :: 3.8
Classifier: Programming Language :: Python :: 3.9
Provides-Extra: docs
Requires-Dist: recommonmark (>=0.6,<0.7); extra == "docs"
Requires-Dist: requests (>=2.24.0,<3.0.0)
Requires-Dist: sphinx (>=3,<4); extra == "docs"
Project-URL: Documentation, https://github.com/newmediaresearch/vidispine-adapter
Project-URL: Repository, https://github.com/newmediaresearch/vidispine-adapter
